image_scraper/utils.py
image_scraper/exceptions.py
image_scraper/progressbar.py
image_scraper/mains.py
image_scraper/__init__.py
ImageScraper-2.0.6.dist-info/metadata.json
ImageScraper-2.0.6.dist-info/METADATA
ImageScraper-2.0.6.dist-info/DESCRIPTION.rst
ImageScraper-2.0.6.dist-info/entry_points.txt
ImageScraper-2.0.6.dist-info/top_level.txt
ImageScraper-2.0.6.dist-info/pbr.json
ImageScraper-2.0.6.dist-info/RECORD
ImageScraper-2.0.6.dist-info/WHEEL
